sxdm/SXDM.py
sxdm/__init__.py
sxdm/alignment.py
sxdm/background.py
sxdm/chi_determination.py
sxdm/clicks.py
sxdm/config.py
sxdm/depreciated.py
sxdm/det_chan.py
sxdm/generalize.py
sxdm/h5.py
sxdm/importer.py
sxdm/logger.py
sxdm/mis.py
sxdm/multi.py
sxdm/multi_update.py
sxdm/pixel.py
sxdm/postprocess.py
sxdm/preprocess.py
sxdm/qt_centroid_viewer.py
sxdm/readingmda.py
sxdm/roi.py
sxdm/roi_bounding.py
sxdm/summed2d.py
sxdm/viewer.py
sxdm-1.0.0.dist-info/LICENSE.txt
sxdm-1.0.0.dist-info/METADATA
sxdm-1.0.0.dist-info/WHEEL
sxdm-1.0.0.dist-info/top_level.txt
sxdm-1.0.0.dist-info/RECORD
