Metadata-Version: 2.1
Name: sxdm
Version: 1.0.0
Summary: Tools for analyzing Scanning X-ray Diffraction Microscopy data
Home-page: https://github.com/WilliamJudge94/sxdm
Author: William Judge
Author-email: williamjudge94@gmail.com
License: UNKNOWN
Keywords: SXDM X-ray microscopy APS 26-ID-C Argonne Advanced Photon Source
Platform: UNKNOWN
Classifier: Development Status :: 3 - Alpha
Classifier: Intended Audience :: Science/Research
Classifier: License :: OSI Approved :: GNU General Public License v3 or later (GPLv3+)
Classifier: Natural Language :: English
Classifier: Operating System :: POSIX :: Linux
Classifier: Programming Language :: Python :: 3.5
Classifier: Topic :: Scientific/Engineering :: Chemistry
Classifier: Topic :: Scientific/Engineering :: Physics
Classifier: Topic :: Scientific/Engineering :: Visualization
Requires-Python: >=3.6
Requires-Dist: h5py (==2.8.0)
Requires-Dist: matplotlib (>=2.1.0)
Requires-Dist: psutil
Requires-Dist: numpy (>=1.16.1)
Requires-Dist: tqdm (>=4.19.5)
Requires-Dist: tifffile
Requires-Dist: miniutils (>=1.0.1)
Requires-Dist: imageio (>=2.5.0)
Requires-Dist: nose (>=1.3.7)
Requires-Dist: progressbar (>=2.5)
Requires-Dist: scipy (>=1.1.0)
Requires-Dist: opencv-python
Requires-Dist: PyQt5
Requires-Dist: pyparsing (==2.4.7)
Requires-Dist: docutils (<0.18)
